setup.py
django_shibboleth_remoteuser_kennydude.egg-info/PKG-INFO
django_shibboleth_remoteuser_kennydude.egg-info/SOURCES.txt
django_shibboleth_remoteuser_kennydude.egg-info/dependency_links.txt
django_shibboleth_remoteuser_kennydude.egg-info/top_level.txt
shibboleth/__init__.py
shibboleth/app_settings.py
shibboleth/backends.py
shibboleth/context_processors.py
shibboleth/decorators.py
shibboleth/middleware.py
shibboleth/models.py
shibboleth/urls.py
shibboleth/views.py
shibboleth/tests/__init__.py
shibboleth/tests/shib.py