Metadata-Version: 1.0
Name: django-shibboleth-remoteuser-kennydude
Version: 0.6
Summary: UNKNOWN
Home-page: https://github.com/Brown-University-Library/django-shibboleth-remoteuser
Author: Ted Lawless
Author-email: tlawless@brown.edu
License: UNKNOWN
Platform: UNKNOWN
